TwodGame/__init__.py
TwodGame/rendering.py
TwodGame/utils/__init__.py
TwodGame/utils/cells.py
TwodGame/utils/player.py
twodgame-0.1.1.dist-info/METADATA
twodgame-0.1.1.dist-info/WHEEL
twodgame-0.1.1.dist-info/RECORD
