Metadata-Version: 2.1
Name: Twodgame
Version: 0.1.1
Summary: Tools to make a 2D game
Author: Your Name
Author-email: you@example.com
Requires-Python: >=3.11,<4.0
Classifier: Programming Language :: Python :: 3
Classifier: Programming Language :: Python :: 3.11
Classifier: Programming Language :: Python :: 3.12
Classifier: Programming Language :: Python :: 3.13
Requires-Dist: keyengine (>=0.0.2,<0.0.3)
